__init__.py
novoteste.py
novoteste-0.0.1.dist-info/LICENSE
novoteste-0.0.1.dist-info/METADATA
novoteste-0.0.1.dist-info/WHEEL
novoteste-0.0.1.dist-info/entry_points.txt
novoteste-0.0.1.dist-info/top_level.txt
novoteste-0.0.1.dist-info/RECORD
