Metadata-Version: 2.1
Name: novoteste
Version: 0.0.1
Summary: Analise fundamentalista utilizando dados de demonstrativos contábeis de empresas listadas B3.
Author-email: Andre Amorim <andre.a.silveira@icloud.com>
Project-URL: Homepage, https://github.com/pypa/sampleproject
Project-URL: Bug Tracker, https://github.com/pypa/sampleproject/issues
Classifier: Programming Language :: Python :: 3
Classifier: License :: OSI Approved :: MIT License
Classifier: Operating System :: OS Independent
Requires-Python: >=3.7
License-File: LICENSE
